dyn/drawing/__init__.py
dyn/drawing/main_draw_sankey.py
dyn/drawing/metrics_figures.py
dyn/drawing/sankey_drawing.py
dyn/drawing/sankey_optimization.py
dyn_viz-0.1.0.dist-info/licenses/LICENSE
dyn_viz-0.1.0.dist-info/METADATA
dyn_viz-0.1.0.dist-info/WHEEL
dyn_viz-0.1.0.dist-info/top_level.txt
dyn_viz-0.1.0.dist-info/RECORD
